odoo/addons/l10n_ch_account_tags/README.rst
odoo/addons/l10n_ch_account_tags/__init__.py
odoo/addons/l10n_ch_account_tags/__manifest__.py
odoo/addons/l10n_ch_account_tags/data/account_account_tag.xml
odoo/addons/l10n_ch_account_tags/data/account_account_template.xml
odoo/addons/l10n_ch_account_tags/i18n/de.po
odoo/addons/l10n_ch_account_tags/i18n/l10n_ch_account_tags.pot
odoo/addons/l10n_ch_account_tags/readme/CONTRIBUTORS.rst
odoo/addons/l10n_ch_account_tags/readme/DESCRIPTION.rst
odoo/addons/l10n_ch_account_tags/readme/HISTORY.rst
odoo/addons/l10n_ch_account_tags/readme/ROADMAP.rst
odoo/addons/l10n_ch_account_tags/readme/USAGE.rst
odoo/addons/l10n_ch_account_tags/static/description/icon.png
odoo/addons/l10n_ch_account_tags/static/description/index.html
odoo11_addon_l10n_ch_account_tags-11.0.1.0.0.99.dev12.dist-info/METADATA
odoo11_addon_l10n_ch_account_tags-11.0.1.0.0.99.dev12.dist-info/WHEEL
odoo11_addon_l10n_ch_account_tags-11.0.1.0.0.99.dev12.dist-info/top_level.txt
odoo11_addon_l10n_ch_account_tags-11.0.1.0.0.99.dev12.dist-info/RECORD
